wasmite/__init__.py
wasmite/globals.py
wasmite/wasi.py
wasmite/wasm.py
wasmite/wat.py
wasmite-0.2.1.dist-info/LICENSE
wasmite-0.2.1.dist-info/METADATA
wasmite-0.2.1.dist-info/WHEEL
wasmite-0.2.1.dist-info/top_level.txt
wasmite-0.2.1.dist-info/RECORD
