Metadata-Version: 2.1
Name: wasmite
Version: 0.2.1
Summary: Wasmite: Webassembly is the future but now it has a testing toolchain
Home-page: https://github.com/yusuf8ahmed/Wasmite
Author: Yusuf Ahmed
Author-email: yusufahmed172@gmail.com
License: UNKNOWN
Keywords: wasmer,wasmite,wasp,wasm,debug,debugging,unit,unit testing,unit tests,unit testing wasm,unit tests wasm,debug wasm,debugging wasm
Platform: any
Classifier: Programming Language :: Python :: 3
Classifier: Development Status :: 2 - Pre-Alpha
Classifier: Operating System :: OS Independent
Classifier: Intended Audience :: Developers
Classifier: Topic :: Internet
Classifier: Topic :: Internet :: WWW/HTTP :: Browsers
Classifier: Topic :: Internet :: WWW/HTTP :: HTTP Servers
Classifier: Topic :: Internet :: WWW/HTTP :: WSGI
Classifier: Topic :: Internet :: WWW/HTTP :: WSGI :: Application
Classifier: Topic :: Internet :: WWW/HTTP :: WSGI :: Middleware
Classifier: Topic :: Internet :: WWW/HTTP :: WSGI :: Server
Classifier: Topic :: Software Development :: Assemblers
Classifier: Topic :: Software Development :: Testing
Classifier: Topic :: Software Development :: Quality Assurance
Classifier: Topic :: System :: Monitoring
Requires-Python: !=3.9, !=2.*
Requires-Dist: loguru
Requires-Dist: wasmer (>=1.0.0-alpha3)
Requires-Dist: wasmer-compiler-cranelift (>=1.0.0-alpha3)
